cve_bot/__init__.py
cve_bot/actions.py
cve_bot/alembic.ini
cve_bot/config.py
cve_bot/conftest.py
cve_bot/db.py
cve_bot/formatters.py
cve_bot/handlers.py
cve_bot/main.py
cve_bot/messages.py
cve_bot/models.py
cve_bot/notifications.py
cve_bot/perf.py
cve_bot/updaters.py
cve_bot/migrations/__init__.py
cve_bot/migrations/env.py
cve_bot/migrations/versions/f698438c140b_initial.py
cve_bot/tests/__init__.py
cve_bot/tests/test_actions.py
cve_bot/tests/test_messages.py
cve_bot/tests/test_notifications.py
cve_bot/tests/test_updaters.py
cve_bot-1.0.0.dist-info/LICENSE
cve_bot-1.0.0.dist-info/METADATA
cve_bot-1.0.0.dist-info/WHEEL
cve_bot-1.0.0.dist-info/entry_points.txt
cve_bot-1.0.0.dist-info/top_level.txt
cve_bot-1.0.0.dist-info/RECORD
