Metadata-Version: 2.1
Name: cve-bot
Version: 1.0.0
Summary: CVE Telegram bot.
Home-page: https://github.com/weastur/cve_bot
Author: Pavel Sapezhko
Author-email: me@weastur.com
License: MIT
Platform: UNKNOWN
Classifier: Development Status :: 5 - Production/Stable
Classifier: Environment :: Web Environment
Classifier: Intended Audience :: Developers
Classifier: Intended Audience :: Information Technology
Classifier: Intended Audience :: System Administrators
Classifier: License :: OSI Approved :: MIT License
Classifier: Natural Language :: English
Classifier: Operating System :: POSIX
Classifier: Programming Language :: Python
Classifier: Programming Language :: Python :: 3
Classifier: Programming Language :: Python :: 3.9
Classifier: Programming Language :: Python :: Implementation :: CPython
Classifier: Topic :: Security
Classifier: Topic :: System
Classifier: Topic :: System :: Operating System
Classifier: Topic :: System :: Systems Administration
Requires-Dist: python-telegram-bot (==13.5)
Requires-Dist: logzio-python-handler (==3.0.0)
Requires-Dist: sentry-sdk (==1.1.0)
Requires-Dist: alembic (==1.6.2)
Requires-Dist: SQLAlchemy (==1.4.15)
Requires-Dist: requests (==2.25.1)
Requires-Dist: ujson (==4.0.2)
Provides-Extra: dev
Requires-Dist: setuptools (==56.2.0) ; extra == 'dev'
Requires-Dist: wheel (==0.36.2) ; extra == 'dev'
Requires-Dist: build (==0.3.1.post1) ; extra == 'dev'
Requires-Dist: twine (==3.4.1) ; extra == 'dev'
Requires-Dist: black (==21.5b1) ; extra == 'dev'
Requires-Dist: coverage (==5.5) ; extra == 'dev'
Requires-Dist: codecov (==2.1.11) ; extra == 'dev'
Requires-Dist: isort (==5.8.0) ; extra == 'dev'
Requires-Dist: wemake-python-styleguide (==0.15.2) ; extra == 'dev'
Requires-Dist: dikort (==0.2.1) ; extra == 'dev'
Requires-Dist: pytest (==6.2.4) ; extra == 'dev'
Requires-Dist: pytest-cov (==2.11.1) ; extra == 'dev'
Requires-Dist: ansible (==3.4.0) ; extra == 'dev'
